codal_tsetmc_datastore/__init__.py
codal_tsetmc_datastore/codal/__init__.py
codal_tsetmc_datastore/codal/utils.py
codal_tsetmc_datastore/codal/financials/__init__.py
codal_tsetmc_datastore/codal/financials/utils.py
codal_tsetmc_datastore/codal/financials/cell/__init__.py
codal_tsetmc_datastore/codal/financials/cell/constants.py
codal_tsetmc_datastore/codal/financials/cell/models.py
codal_tsetmc_datastore/codal/financials/cell/utils.py
codal_tsetmc_datastore/codal/financials/header/__init__.py
codal_tsetmc_datastore/codal/financials/header/models.py
codal_tsetmc_datastore/codal/financials/header/utils.py
codal_tsetmc_datastore/codal/financials/letter/__init__.py
codal_tsetmc_datastore/codal/financials/letter/models.py
codal_tsetmc_datastore/codal/financials/letter/utils.py
codal_tsetmc_datastore/codal/financials/sheet/__init__.py
codal_tsetmc_datastore/codal/financials/sheet/constants.py
codal_tsetmc_datastore/codal/financials/sheet/models.py
codal_tsetmc_datastore/codal/financials/sheet/utils.py
codal_tsetmc_datastore/codal/financials/table/__init__.py
codal_tsetmc_datastore/codal/financials/table/constants.py
codal_tsetmc_datastore/codal/financials/table/models.py
codal_tsetmc_datastore/codal/financials/table/utils.py
codal_tsetmc_datastore/tools/__init__.py
codal_tsetmc_datastore/tools/constants.py
codal_tsetmc_datastore/tools/utils.py
codal_tsetmc_datastore-3.0.8.dist-info/licenses/LICENSE.txt
pyarmor_runtime_000000/__init__.py
pyarmor_runtime_000000/pyarmor_runtime.so
codal_tsetmc_datastore-3.0.8.dist-info/METADATA
codal_tsetmc_datastore-3.0.8.dist-info/WHEEL
codal_tsetmc_datastore-3.0.8.dist-info/top_level.txt
codal_tsetmc_datastore-3.0.8.dist-info/RECORD
