Metadata-Version: 2.4
Name: codal-tsetmc-datastore
Version: 3.0.8
Summary: Private datastore module for codal-tsetmc
Author-email: Mohsen Ebrahimi <mohsenebrahimy.ir@gmail.com>
License-Expression: MIT
Project-URL: Homepage, https://github.com/mohsenebrahimyir/codal-tsetmc-datastore
Project-URL: Repository, https://github.com/mohsenebrahimyir/codal-tsetmc-datastore
Requires-Python: >=3.10
License-File: LICENSE.txt
Requires-Dist: codal-tsetmc>=3.0.9
Provides-Extra: dev
Requires-Dist: pyarmor>=9.1.7; extra == "dev"
Requires-Dist: pyarmor.cli.core>=7.6.7; extra == "dev"
Dynamic: license-file
